torchprint/__init__.py
torchprint/torchprint.py
torchprint-0.1.1.dist-info/LICENSE
torchprint-0.1.1.dist-info/METADATA
torchprint-0.1.1.dist-info/WHEEL
torchprint-0.1.1.dist-info/top_level.txt
torchprint-0.1.1.dist-info/RECORD
